[
    {
      "inputs": [
        {
          "internalType": "address",
          "name": "_token",
          "type": "address"
        },
        {
          "internalType": "uint256[]",
          "name": "taskIds",
          "type": "uint256[]"
        },
        {
          "internalType": "uint256[]",
          "name": "merkleRoots",
          "type": "uint256[]"
        }
      ],
      "stateMutability": "nonpayable",
      "type": "constructor"
    },
    {
      "anonymous": false,
      "inputs": [
        {
          "indexed": true,
          "internalType": "address",
          "name": "user",
          "type": "address"
        },
        {
          "indexed": true,
          "internalType": "uint256",
          "name": "taskId",
          "type": "uint256"
        },
        {
          "indexed": false,
          "internalType": "uint256",
          "name": "amount",
          "type": "uint256"
        }
      ],
      "name": "AirDropClaim",
      "type": "event"
    },
    {
      "inputs": [
        {
          "internalType": "uint256",
          "name": "taskId",
          "type": "uint256"
        },
        {
          "internalType": "uint256",
          "name": "amount",
          "type": "uint256"
        },
        {
          "internalType": "bytes32[]",
          "name": "merkleProof",
          "type": "bytes32[]"
        }
      ],
      "name": "claim",
      "outputs": [],
      "stateMutability": "nonpayable",
      "type": "function"
    },
    {
      "inputs": [
        {
          "internalType": "uint256",
          "name": "",
          "type": "uint256"
        },
        {
          "internalType": "address",
          "name": "",
          "type": "address"
        }
      ],
      "name": "claimStatus",
      "outputs": [
        {
          "internalType": "bool",
          "name": "",
          "type": "bool"
        }
      ],
      "stateMutability": "view",
      "type": "function"
    },
    {
      "inputs": [
        {
          "internalType": "uint256",
          "name": "taskId",
          "type": "uint256"
        }
      ],
      "name": "getMerkleRoot",
      "outputs": [
        {
          "internalType": "bytes32",
          "name": "",
          "type": "bytes32"
        }
      ],
      "stateMutability": "view",
      "type": "function"
    },
    {
      "inputs": [
        {
          "internalType": "uint256",
          "name": "taskId",
          "type": "uint256"
        }
      ],
      "name": "getReward",
      "outputs": [
        {
          "internalType": "uint256",
          "name": "",
          "type": "uint256"
        }
      ],
      "stateMutability": "view",
      "type": "function"
    },
    {
      "inputs": [
        {
          "internalType": "uint256",
          "name": "",
          "type": "uint256"
        }
      ],
      "name": "merkleRootMap",
      "outputs": [
        {
          "internalType": "bytes32",
          "name": "",
          "type": "bytes32"
        }
      ],
      "stateMutability": "view",
      "type": "function"
    },
    {
      "inputs": [
        {
          "internalType": "uint256",
          "name": "",
          "type": "uint256"
        }
      ],
      "name": "rewardMap",
      "outputs": [
        {
          "internalType": "uint256",
          "name": "",
          "type": "uint256"
        }
      ],
      "stateMutability": "view",
      "type": "function"
    },
    {
      "inputs": [
        {
          "internalType": "uint256[]",
          "name": "taskIds",
          "type": "uint256[]"
        },
        {
          "internalType": "bytes32[]",
          "name": "merkleRoots",
          "type": "bytes32[]"
        }
      ],
      "name": "setMerkleRoot",
      "outputs": [],
      "stateMutability": "nonpayable",
      "type": "function"
    },
    {
      "inputs": [
        {
          "internalType": "uint256[]",
          "name": "taskIds",
          "type": "uint256[]"
        },
        {
          "internalType": "uint256[]",
          "name": "amounts",
          "type": "uint256[]"
        }
      ],
      "name": "setReward",
      "outputs": [],
      "stateMutability": "nonpayable",
      "type": "function"
    }
  ]